{
  "timestamp": "2025-10-25T11:00:00",
  "outdoor": {
    "temperature": 28.2,
    "feelsLike": 29.1,
    "dewPoint": 18.1,
    "humidity": 54.0
  },
  "wind": {
    "speed": 5.4,
    "gust": 7.2,
    "maxDailyGust": 20.2,
    "directionDeg": 205
  },
  "rain": {
    "hourly": 0.0,
    "daily": 0.0,
    "weekly": 10.9,
    "monthly": 139.7,
    "yearly": 319.8,
    "total": 319.8
  },
  "pressure": {
    "relative": 1017.9,
    "absolute": 927.4
  },
  "solar": {
    "uv": 7,
    "radiation": 486.7
  },
  "indoor": {
    "temperature": 26.8,
    "humidity": 62.0
  }
}