{
  "timestamp": "2025-10-12T09:00:00",
  "outdoor": {
    "temperature": 27.0,
    "feelsLike": 28.0,
    "dewPoint": 18.0,
    "humidity": 58.0
  },
  "wind": {
    "speed": 1.4,
    "gust": 5.4,
    "maxDailyGust": 14.8,
    "directionDeg": 96
  },
  "rain": {
    "hourly": 0.0,
    "daily": 0.0,
    "weekly": 43.2,
    "monthly": 110.8,
    "yearly": 290.9,
    "total": 290.9
  },
  "pressure": {
    "relative": 1018.1,
    "absolute": 927.5
  },
  "solar": {
    "uv": 5,
    "radiation": 508.9
  },
  "indoor": {
    "temperature": 26.8,
    "humidity": 64.0
  }
}