{
  "timestamp": "2025-10-04T11:00:00",
  "outdoor": {
    "temperature": 25.9,
    "feelsLike": 26.4,
    "dewPoint": 20.2,
    "humidity": 71.0
  },
  "wind": {
    "speed": 1.4,
    "gust": 3.6,
    "maxDailyGust": 9.4,
    "directionDeg": 265
  },
  "rain": {
    "hourly": 0.0,
    "daily": 0.0,
    "weekly": 13.5,
    "monthly": 13.5,
    "yearly": 193.6,
    "total": 193.6
  },
  "pressure": {
    "relative": 1020.5,
    "absolute": 930.0
  },
  "solar": {
    "uv": 2,
    "radiation": 294.9
  },
  "indoor": {
    "temperature": 27.0,
    "humidity": 70.0
  }
}