{
  "timestamp": "2025-12-02T18:00:00",
  "outdoor": {
    "temperature": 23.4,
    "feelsLike": 23.8,
    "dewPoint": 19.0,
    "humidity": 76.0
  },
  "wind": {
    "speed": 5.4,
    "gust": 13.0,
    "maxDailyGust": 22.0,
    "directionDeg": 48
  },
  "rain": {
    "hourly": 0.0,
    "daily": 0.0,
    "weekly": 0.0,
    "monthly": 0.0,
    "yearly": 322.1,
    "total": 322.1
  },
  "pressure": {
    "relative": 1016.6,
    "absolute": 926.2
  },
  "solar": {
    "uv": 0,
    "radiation": 0.0
  },
  "indoor": {
    "temperature": 25.3,
    "humidity": 68.0
  }
}