{
  "bucketHour": "2026-01-28 12:00",
  "timestamp": "2026-01-28T12:00:00",
  "source": "google-sheet-backfill",
  "outdoor": {
    "temperature": 28.5,
    "feelsLike": 28.0,
    "dewPoint": 13.2,
    "humidity": 39
  },
  "wind": {
    "speed": 0.7,
    "gust": 3.6,
    "maxDailyGust": 16.6,
    "directionDeg": 50
  },
  "rain": {
    "hourly": 0.0,
    "daily": 0.0,
    "weekly": 0.0
  },
  "pressure": {
    "relative": 1021.2,
    "absolute": 930.7
  },
  "indoor": {
    "temperature": 25.7,
    "humidity": 47
  },
  "solar": {
    "uv": 6.0,
    "radiation": 631.4
  }
}