{
  "bucketHour": "2026-01-26 17:00",
  "timestamp": "2026-01-26T17:00:00",
  "source": "google-sheet-backfill",
  "outdoor": {
    "temperature": 22.3,
    "feelsLike": 22.4,
    "dewPoint": 16.5,
    "humidity": 70
  },
  "wind": {
    "speed": 0.0,
    "gust": 0.0,
    "maxDailyGust": 25.6,
    "directionDeg": 113
  },
  "rain": {
    "hourly": 0.0,
    "daily": 0.0,
    "weekly": 0.0
  },
  "pressure": {
    "relative": 1021.4,
    "absolute": 930.9
  },
  "indoor": {
    "temperature": 23.9,
    "humidity": 63
  },
  "solar": {
    "uv": 0.0,
    "radiation": 15.1
  }
}