{
  "timestamp": "2025-10-02T23:00:00",
  "outdoor": {
    "temperature": 20.9,
    "feelsLike": 21.3,
    "dewPoint": 19.0,
    "humidity": 89.0
  },
  "wind": {
    "speed": 0.0,
    "gust": 0.0,
    "maxDailyGust": 29.5,
    "directionDeg": 227
  },
  "rain": {
    "hourly": 0.0,
    "daily": 3.8,
    "weekly": 3.8,
    "monthly": 3.8,
    "yearly": 183.9,
    "total": 183.9
  },
  "pressure": {
    "relative": 1018.2,
    "absolute": 927.8
  },
  "solar": {
    "uv": 0,
    "radiation": 0.0
  },
  "indoor": {
    "temperature": 25.9,
    "humidity": 70.0
  }
}