{
  "timestamp": "2025-12-21T15:00:00",
  "outdoor": {
    "temperature": 26.6,
    "feelsLike": 26.4,
    "dewPoint": 11.5,
    "humidity": 39.0
  },
  "wind": {
    "speed": 2.5,
    "gust": 5.4,
    "maxDailyGust": 25.6,
    "directionDeg": 129
  },
  "rain": {
    "hourly": 0.0,
    "daily": 0.0,
    "weekly": 0.0,
    "monthly": 1.8,
    "yearly": 323.9,
    "total": 323.9
  },
  "pressure": {
    "relative": 1016.8,
    "absolute": 926.3
  },
  "solar": {
    "uv": 2,
    "radiation": 256.1
  },
  "indoor": {
    "temperature": 23.8,
    "humidity": 46.0
  }
}